apg_py/__init__.py
apg_py/__main__.py
apg_py/generator.py
apg_py/api/__init__.py
apg_py/api/api.py
apg_py/api/rule_attributes.py
apg_py/api/rule_dependencies.py
apg_py/api/sabnf_grammar.py
apg_py/api/scanner.py
apg_py/api/scanner_callbacks.py
apg_py/api/scanner_grammar.py
apg_py/api/semantic.py
apg_py/api/semantic_callbacks.py
apg_py/api/syntax.py
apg_py/api/syntax_callbacks.py
apg_py/exp/__init__.py
apg_py/exp/exp.py
apg_py/lib/__init__.py
apg_py/lib/ast.py
apg_py/lib/backreferences.py
apg_py/lib/identifiers.py
apg_py/lib/parser.py
apg_py/lib/stats.py
apg_py/lib/trace.py
apg_py/lib/utilities.py
apg_py-1.0.3.dist-info/LICENSE
apg_py-1.0.3.dist-info/METADATA
apg_py-1.0.3.dist-info/WHEEL
apg_py-1.0.3.dist-info/entry_points.txt
apg_py-1.0.3.dist-info/top_level.txt
apg_py-1.0.3.dist-info/RECORD
