Metadata-Version: 2.1
Name: apg_py
Version: 1.0.3
Summary: Python APG - an ABNF parser generator.
Author-email: Lowell Thomas <ldt@sabnf.com>
License: BSD 2-Clause License
Project-URL: Homepage, https://github.com/ldthomas/apg-py
Project-URL: Bug Tracker, https://github.com/ldthomas/apg-py/issues
Classifier: Programming Language :: Python :: 3
Classifier: License :: OSI Approved :: BSD License
Classifier: Operating System :: OS Independent
Requires-Python: >=3.7
License-File: LICENSE
